raspberry_epaper/__init__.py
raspberry_epaper/cli.py
raspberry_epaper/combine.py
raspberry_epaper/epd.py
raspberry_epaper/epd_core.py
raspberry_epaper/filepath.py
raspberry_epaper/font/NotoSansJP-Regular.otf
raspberry_epaper/font/OFL.txt
raspberry_epaper/get_background_color.py
raspberry_epaper/print.py
raspberry_epaper/type.py
raspberry_epaper/valid_types.py
raspberry_epaper-1.5.0.dist-info/entry_points.txt
raspberry_epaper-1.5.0.dist-info/LICENSE
raspberry_epaper-1.5.0.dist-info/WHEEL
raspberry_epaper-1.5.0.dist-info/METADATA
raspberry_epaper-1.5.0.dist-info/RECORD
