Metadata-Version: 2.1
Name: raspberry-epaper
Version: 1.5.0
Summary: A tool to easily use waveshare's e-paper module with Raspberry Pi
Home-page: https://github.com/yskoht/raspberry-epaper
License: MIT
Author: yskoht
Author-email: ysk.oht@gmail.com
Requires-Python: >=3.7,<3.11
Classifier: License :: OSI Approved :: MIT License
Classifier: Programming Language :: Python :: 3
Classifier: Programming Language :: Python :: 3.10
Classifier: Programming Language :: Python :: 3.7
Classifier: Programming Language :: Python :: 3.8
Classifier: Programming Language :: Python :: 3.9
Classifier: Topic :: Software Development :: Libraries :: Python Modules
Requires-Dist: Pillow (>=8.4.0,<9.0.0)
Requires-Dist: numpy (>=1.21.4,<2.0.0)
Requires-Dist: python-box (>=5.4.1,<6.0.0)
Requires-Dist: qrcode (>=7.3.1,<8.0.0)
Requires-Dist: typer (>=0.4.0,<0.5.0)
Requires-Dist: waveshare-epaper (>=1.1.1,<2.0.0)
Project-URL: Repository, https://github.com/yskoht/raspberry-epaper
